{
  "version": "0.2",
  "language": "en",
  "words": [
    "AAP",
    "Ansible",
    "bgrimmet",
    "CoP",
    "cspell",
    "FQCN",
    "gaurav",
    "Grimmet",
    "infra",
    "Jinja",
    "markdownlint",
    "nosborn",
    "pyyaml",
    "redhat",
    "SSOT",
    "yamllint",
    "automationplatform",
    "GitOps",
    "idempotency",
    "idempotent",
    "playbook",
    "playbooks",
    "rulebook",
    "rulebooks",
    "scm",
    "workflow",
    "workflows"
  ],
  "ignorePaths": [
    "node_modules/**",
    ".git/**",
    "*.json",
    "package-lock.json"
  ],
  "ignoreRegExpList": [
    "/```[\\s\\S]*?```/g",
    "/`[^`]*`/g",
    "/https?:\\/\\/[^\\s]*/g"
  ]
}
